{"@type":"morel.dqmsl.party.model.Monster","no":197,"name":"メイジももんじゃ","icon":"/img/icon/000197.gif","viewedNum":2411,"likeNum":5,"dislikeNum":0,"rank":{"name":"A","ordinal":2},"type":{"name":"REC","ordinal":2},"system":{"name":"BEAST","ordinal":2},"weight":2,"maxLevel":40,"hp":159,"mp":92,"offense":119,"defense":142,"dexterity":130,"intelligent":158,"resistances":{"@type":"java.util.TreeMap","@keys":[{"@type":"morel.dqmsl.party.model.Monster$ResistanceType","name":"FIRE","ordinal":0},{"@type":"morel.dqmsl.party.model.Monster$ResistanceType","name":"ICE","ordinal":1},{"@type":"morel.dqmsl.party.model.Monster$ResistanceType","name":"THANDER","ordinal":2},{"@type":"morel.dqmsl.party.model.Monster$ResistanceType","name":"INMAGIC","ordinal":8},{"@type":"morel.dqmsl.party.model.Monster$ResistanceType","name":"SLEEP","ordinal":11}],"@items":[{"@type":"morel.dqmsl.party.model.Monster$ResistanceReaction","name":"HELF","ordinal":3},{"@id":1,"@type":"morel.dqmsl.party.model.Monster$ResistanceReaction","name":"WEEK","ordinal":6},{"@ref":1},{"@type":"morel.dqmsl.party.model.Monster$ResistanceReaction","name":"VOID","ordinal":2},{"@ref":1}]},"skills":{"@type":"java.util.TreeMap","1005":{"@type":"morel.dqmsl.party.model.Skill","id":"1005","name":"イオ","typeId":"10","typeName":"攻撃呪文","type":{"id":"10","name":"攻撃呪文"}},"1007":{"@type":"morel.dqmsl.party.model.Skill","id":"1007","name":"ヒャド","typeId":"10","typeName":"攻撃呪文","type":{"id":"10","name":"攻撃呪文"}}}}