{"@type":"morel.dqmsl.party.model.Monster","no":1003,"name":"カンダタこぶん","icon":"/img/icon/001003.gif","viewedNum":77454,"likeNum":52,"dislikeNum":9,"rank":{"name":"E","ordinal":6},"type":{"name":"ATT","ordinal":0},"system":{"name":"MAOU","ordinal":7},"weight":14,"maxLevel":80,"hp":530,"mp":186,"offense":401,"defense":332,"dexterity":348,"intelligent":202,"resistances":{"@type":"java.util.TreeMap","@keys":[{"@type":"morel.dqmsl.party.model.Monster$ResistanceType","name":"FIRE","ordinal":0},{"@type":"morel.dqmsl.party.model.Monster$ResistanceType","name":"ICE","ordinal":1},{"@type":"morel.dqmsl.party.model.Monster$ResistanceType","name":"WIND","ordinal":3},{"@type":"morel.dqmsl.party.model.Monster$ResistanceType","name":"DARK","ordinal":6},{"@type":"morel.dqmsl.party.model.Monster$ResistanceType","name":"DEATH","ordinal":7},{"@type":"morel.dqmsl.party.model.Monster$ResistanceType","name":"TOXIC","ordinal":10},{"@type":"morel.dqmsl.party.model.Monster$ResistanceType","name":"SLEEP","ordinal":11},{"@type":"morel.dqmsl.party.model.Monster$ResistanceType","name":"CONFUSION","ordinal":12}],"@items":[{"@id":1,"@type":"morel.dqmsl.party.model.Monster$ResistanceReaction","name":"HELF","ordinal":3},{"@ref":1},{"@id":3,"@type":"morel.dqmsl.party.model.Monster$ResistanceReaction","name":"WEEK","ordinal":6},{"@id":2,"@type":"morel.dqmsl.party.model.Monster$ResistanceReaction","name":"VOID","ordinal":2},{"@ref":1},{"@ref":2},{"@ref":1},{"@ref":3}]},"skills":{"@type":"java.util.TreeMap","4001":{"@type":"morel.dqmsl.party.model.Skill","id":"4001","name":"バイキルト","typeId":"40","typeName":"補助アップ呪文","type":{"id":"40","name":"補助アップ呪文"}},"7038":{"@type":"morel.dqmsl.party.model.Skill","id":"7038","name":"武器ふりまわし","typeId":"70","typeName":"斬撃状態異常","type":{"id":"70","name":"斬撃状態異常"}}}}